LICENSE
MANIFEST.in
README.rst
setup.py
pag/__init__.py
pag/app.py
pag/client.py
pag/utils.py
pag.egg-info/PKG-INFO
pag.egg-info/SOURCES.txt
pag.egg-info/dependency_links.txt
pag.egg-info/entry_points.txt
pag.egg-info/not-zip-safe
pag.egg-info/top_level.txt
pag/commands/__init__.py
pag/commands/clone.py
pag/commands/create.py
pag/commands/createissue.py
pag/commands/fork.py
pag/commands/gitaliasing.py
pag/commands/pullrequest.py
pag/commands/remote.py
pag/commands/review.py
pag/commands/upload.py
test/test_clone.py
test/test_review.py
test/test_utils.py