Metadata-Version: 1.1
Name: pag
Version: 0.8
Summary: Commandline interaction with pagure.io
Home-page: https://pagure.io/pag
Author: Ralph Bean
Author-email: rbean@redhat.com
License: GPLv3+
Platform: UNKNOWN
Classifier: License :: OSI Approved :: GNU General Public License v3 or later (GPLv3+)
Classifier: Programming Language :: Python :: 3 :: Only
